showbotlib/__init__.py
showbotlib/models.py
showbotlib/showbot.py
showbotlib/telegramclient.py
showbotlib/tv_program.py
showbotlib-0.0.1.dist-info/METADATA
showbotlib-0.0.1.dist-info/WHEEL
showbotlib-0.0.1.dist-info/top_level.txt
showbotlib-0.0.1.dist-info/RECORD
